git_processor/__init__.py
git_processor/data.py
git_processor/name_linter.py
git_processor/parser.py
git_processor/stats.py
processor/__init__.py
processor/app.py
processor/name_linter.py
processor/parser.py
src/__init__.py
src/app.py
src/name_linter.py
src/parser.py
tests/__init__.py
tests/test_name_lint.py
tests/test_parser.py
git_processor-0.7.dist-info/METADATA
git_processor-0.7.dist-info/WHEEL
git_processor-0.7.dist-info/top_level.txt
git_processor-0.7.dist-info/RECORD
