Metadata-Version: 2.1
Name: git-processor
Version: 0.7
Summary: Process and parse through git log statistic
Home-page: https://github.com/sylhare/git-git_processor
Author: sylhare
Author-email: sylhare@outlook.com
License: UNKNOWN
Keywords: git git_processor data science
Platform: UNKNOWN
Classifier: Development Status :: 3 - Alpha
Classifier: Programming Language :: Python :: 3.6
Requires-Dist: pandas
Requires-Dist: matplotlib
